ovos_PHAL_rediscamera/__init__.py
ovos_PHAL_rediscamera/__main__.py
ovos_PHAL_rediscamera/server.py
ovos_PHAL_rediscamera/version.py
ovos_PHAL_rediscamera-0.0.0a3.dist-info/METADATA
ovos_PHAL_rediscamera-0.0.0a3.dist-info/WHEEL
ovos_PHAL_rediscamera-0.0.0a3.dist-info/entry_points.txt
ovos_PHAL_rediscamera-0.0.0a3.dist-info/top_level.txt
ovos_PHAL_rediscamera-0.0.0a3.dist-info/zip-safe
ovos_PHAL_rediscamera-0.0.0a3.dist-info/RECORD
