Metadata-Version: 2.1
Name: ovos-PHAL-rediscamera
Version: 0.0.0a3
Summary: Expose OVOS cameras to IOT frameworks
Home-page: https://github.com/OpenVoiceOS/ovos-PHAL-rediscamera
Author: JarbasAi
Author-email: jarbasai@mailfence.com
License: Apache-2.0
Platform: UNKNOWN
Classifier: Development Status :: 3 - Alpha
Classifier: Intended Audience :: Developers
Classifier: Topic :: Text Processing :: Linguistic
Classifier: License :: OSI Approved :: Apache Software License
Classifier: Programming Language :: Python :: 3.5
Classifier: Programming Language :: Python :: 3.6
Requires-Dist: ovos-plugin-manager ~=0.0
Requires-Dist: imutils
Requires-Dist: opencv-python
Requires-Dist: redis
Requires-Dist: flask
Requires-Dist: click
